[
  {
    "title": "北京市",
    "brief": "北京市是一座有着三千多年历史的古都，在不同的朝代有着不同的称谓，大致算起来有二十多个别称。作为中国四大古都之一，有很多地方特色的民风习俗：北京小吃、京剧、京韵大鼓、相声、舞台剧、铁板快书、景泰蓝、牙雕、毛猴、漆雕、赛蝈蝈和蝈蝈笼、吹糖人、捏面人等等。",
    "materials": [
      {
        "subtitle": "非遗项目",
        "knowledgeBase": [
          {
            "type": "指南",
            "title": "相声"
          },
          {
            "type": "指南",
            "title": "昆曲"
          },
          {
            "type": "指南",
            "title": "大兴诗赋闲"
          }
        ]
      },
      {
        "subtitle": "老字号",
        "knowledgeBase": [
          {
            "type": "指南",
            "title": "全聚德"
          },
          {
            "type": "指南",
            "title": "同仁堂"
          },
          {
            "type": "指南",
            "title": "一得阁"
          }
        ]
      }
    ]
  },
  {
    "title": "广州市",
    "brief": "广州文化主要是属于岭南文化的“广府文化”，客家文化次之。广府文化即广府民系的文化，是指珠三角广州府地区使用粤方言的汉族居民的文化。广州自古以来是广东乃至岭南区域政治、经济和文化中心。在建筑、艺术、宗教、戏剧、音乐、文学、绘画、工艺、饮食、园林、风俗等各个文化领域，处处表现出悠久的历史渊源和鲜明的个性。",
    "materials": [
      {
        "subtitle": "传统美术",
        "knowledgeBase": [
          {
            "type": "指南",
            "title": "广绣"
          },
          {
            "type": "指南",
            "title": "玉雕"
          },
          {
            "type": "指南",
            "title": "榄雕"
          }
        ]
      },
      {
        "subtitle": "民俗",
        "knowledgeBase": [
          {
            "type": "指南",
            "title": "迎春花市"
          },
          {
            "type": "指南",
            "title": "醒狮"
          },
          {
            "type": "指南",
            "title": "龙舟"
          }
        ]
      }

    ]
  },
  {
    "title": "苏州市",
    "brief": "姑苏文化历史源远流长，建城二千五百多年以来，文化积淀十分深厚。在这块得天独厚而又美丽富饶的土地上，世世代代的苏州人在创造物质文明的同时，也创造了灿烂的吴地文化，并以其独树一帜的风格而在华夏文化史上占有着重要的位置。隋开皇九年（589年）灭陈后废吴郡建置，以城西有姑苏山之故，易吴州为苏州，这是苏州得名之始。",
    "materials": [
      {
        "subtitle": "戏曲",
        "knowledgeBase": [
          {
            "type": "媒体",
            "title": "昆剧"
          },
          {
            "type": "媒体",
            "title": "苏剧"
          }
        ]
      }
    ]
  }
]